.hgignore
.hgtags
setup.cfg
setup.py
Products/__init__.py
Products.WebServerAuth.egg-info/PKG-INFO
Products.WebServerAuth.egg-info/SOURCES.txt
Products.WebServerAuth.egg-info/dependency_links.txt
Products.WebServerAuth.egg-info/namespace_packages.txt
Products.WebServerAuth.egg-info/not-zip-safe
Products.WebServerAuth.egg-info/requires.txt
Products.WebServerAuth.egg-info/top_level.txt
Products/WebServerAuth/README.txt
Products/WebServerAuth/__init__.py
Products/WebServerAuth/config.py
Products/WebServerAuth/plugin.py
Products/WebServerAuth/utils.py
Products/WebServerAuth/version.txt
Products/WebServerAuth/zmi.py
Products/WebServerAuth/Extensions/Install.py
Products/WebServerAuth/profiles/default/metadata.xml
Products/WebServerAuth/profiles/default/skins.xml
Products/WebServerAuth/profiles/uninstall/skins.xml
Products/WebServerAuth/skins/webserverauth/login_form.cpt
Products/WebServerAuth/tests/__init__.py
Products/WebServerAuth/tests/base.py
Products/WebServerAuth/tests/test_authentication.py
Products/WebServerAuth/tests/test_challenge.py
Products/WebServerAuth/tests/test_extraction.py
Products/WebServerAuth/tests/test_install.py
Products/WebServerAuth/tests/test_integration.py
Products/WebServerAuth/www/add.pt
Products/WebServerAuth/www/config.pt
Products/WebServerAuth/www/multiplugin.gif