Metadata-Version: 1.0
Name: Products.WebServerAuth
Version: 1.7
Summary: Delegates Plone's authentication concerns to a web server
Home-page: http://plone.org/products/webserverauth
Author: WebLion Group, Penn State
Author-email: support@weblion.psu.edu
License: GPL
Keywords: web zope plone authentication pas zope2
Platform: UNKNOWN
Classifier: Development Status :: 5 - Production/Stable
Classifier: Framework :: Plone
Classifier: Framework :: Zope2
Classifier: Intended Audience :: System Administrators
Classifier: Programming Language :: Python
Classifier: Topic :: Security
Classifier: Topic :: Software Development :: Libraries :: Python Modules
Classifier: Topic :: System :: Systems Administration :: Authentication/Directory
